datauri/__init__.py
datauri/exceptions.py
tests/__init__.py
tests/test_parsing.py
python_datauri_whtsky-0.2.8.dist-info/LICENSE
python_datauri_whtsky-0.2.8.dist-info/METADATA
python_datauri_whtsky-0.2.8.dist-info/WHEEL
python_datauri_whtsky-0.2.8.dist-info/top_level.txt
python_datauri_whtsky-0.2.8.dist-info/RECORD
